{
  "schema": "tf100web-scada-tags-v1",
  "count": 43,
  "tags": [
    {
      "id": "tf100.mapping.161",
      "mapping_id": 161,
      "keyword": 10088,
      "keyword_label": "PE_16",
      "keyword_type": "LECTURE",
      "device_id": 2,
      "device": "NX102 systeme refrigération",
      "protocol_id": 2,
      "protocol": "NX102 OPC UA",
      "addressing_scheme": "OPCUA_NODE",
      "addressing_scheme_label": "OPC UA node id",
      "address_uri": "opcua://ns=4;s=PE_16",
      "address": {
        "node_id": "ns=4;s=PE_16"
      },
      "datatype": "FLOAT32",
      "datatype_label": "Float32",
      "writeable": false,
      "enabled": true,
      "historian": false,
      "poll_period_ms": null,
      "unit": "",
      "scale": 1.0,
      "offset": 0.0,
      "scaling": null,
      "notes": ""
    },
    {
      "id": "tf100.mapping.162",
      "mapping_id": 162,
      "keyword": 10089,
      "keyword_label": "PE_95",
      "keyword_type": "LECTURE",
      "device_id": 2,
      "device": "NX102 systeme refrigération",
      "protocol_id": 2,
      "protocol": "NX102 OPC UA",
      "addressing_scheme": "OPCUA_NODE",
      "addressing_scheme_label": "OPC UA node id",
      "address_uri": "opcua://ns=4;s=PE_95",
      "address": {
        "node_id": "ns=4;s=PE_95"
      },
      "datatype": "FLOAT32",
      "datatype_label": "Float32",
      "writeable": false,
      "enabled": true,
      "historian": false,
      "poll_period_ms": null,
      "unit": "",
      "scale": 1.0,
      "offset": 0.0,
      "scaling": null,
      "notes": ""
    },
    {
      "id": "tf100.mapping.163",
      "mapping_id": 163,
      "keyword": 10090,
      "keyword_label": "PE_96",
      "keyword_type": "LECTURE",
      "device_id": 2,
      "device": "NX102 systeme refrigération",
      "protocol_id": 2,
      "protocol": "NX102 OPC UA",
      "addressing_scheme": "OPCUA_NODE",
      "addressing_scheme_label": "OPC UA node id",
      "address_uri": "opcua://ns=4;s=PE_96",
      "address": {
        "node_id": "ns=4;s=PE_96"
      },
      "datatype": "FLOAT32",
      "datatype_label": "Float32",
      "writeable": false,
      "enabled": true,
      "historian": false,
      "poll_period_ms": null,
      "unit": "",
      "scale": 1.0,
      "offset": 0.0,
      "scaling": null,
      "notes": ""
    },
    {
      "id": "tf100.mapping.164",
      "mapping_id": 164,
      "keyword": 10091,
      "keyword_label": "PE_119",
      "keyword_type": "LECTURE",
      "device_id": 2,
      "device": "NX102 systeme refrigération",
      "protocol_id": 2,
      "protocol": "NX102 OPC UA",
      "addressing_scheme": "OPCUA_NODE",
      "addressing_scheme_label": "OPC UA node id",
      "address_uri": "opcua://ns=4;s=PE_119",
      "address": {
        "node_id": "ns=4;s=PE_119"
      },
      "datatype": "FLOAT32",
      "datatype_label": "Float32",
      "writeable": false,
      "enabled": true,
      "historian": false,
      "poll_period_ms": null,
      "unit": "",
      "scale": 1.0,
      "offset": 0.0,
      "scaling": null,
      "notes": ""
    },
    {
      "id": "tf100.mapping.165",
      "mapping_id": 165,
      "keyword": 10097,
      "keyword_label": "TE_EXT",
      "keyword_type": "LECTURE",
      "device_id": 2,
      "device": "NX102 systeme refrigération",
      "protocol_id": 2,
      "protocol": "NX102 OPC UA",
      "addressing_scheme": "OPCUA_NODE",
      "addressing_scheme_label": "OPC UA node id",
      "address_uri": "opcua://ns=4;s=TE_EXT",
      "address": {
        "node_id": "ns=4;s=TE_EXT"
      },
      "datatype": "FLOAT32",
      "datatype_label": "Float32",
      "writeable": false,
      "enabled": true,
      "historian": false,
      "poll_period_ms": null,
      "unit": "",
      "scale": 1.0,
      "offset": 0.0,
      "scaling": null,
      "notes": ""
    },
    {
      "id": "tf100.mapping.166",
      "mapping_id": 166,
      "keyword": 10098,
      "keyword_label": "TE_117",
      "keyword_type": "LECTURE",
      "device_id": 2,
      "device": "NX102 systeme refrigération",
      "protocol_id": 2,
      "protocol": "NX102 OPC UA",
      "addressing_scheme": "OPCUA_NODE",
      "addressing_scheme_label": "OPC UA node id",
      "address_uri": "opcua://ns=4;s=TE_117",
      "address": {
        "node_id": "ns=4;s=TE_117"
      },
      "datatype": "FLOAT32",
      "datatype_label": "Float32",
      "writeable": false,
      "enabled": true,
      "historian": false,
      "poll_period_ms": null,
      "unit": "",
      "scale": 1.0,
      "offset": 0.0,
      "scaling": null,
      "notes": ""
    },
    {
      "id": "tf100.mapping.167",
      "mapping_id": 167,
      "keyword": 10099,
      "keyword_label": "TE_118",
      "keyword_type": "LECTURE",
      "device_id": 2,
      "device": "NX102 systeme refrigération",
      "protocol_id": 2,
      "protocol": "NX102 OPC UA",
      "addressing_scheme": "OPCUA_NODE",
      "addressing_scheme_label": "OPC UA node id",
      "address_uri": "opcua://ns=4;s=TE_118",
      "address": {
        "node_id": "ns=4;s=TE_118"
      },
      "datatype": "FLOAT32",
      "datatype_label": "Float32",
      "writeable": false,
      "enabled": true,
      "historian": false,
      "poll_period_ms": null,
      "unit": "",
      "scale": 1.0,
      "offset": 0.0,
      "scaling": null,
      "notes": ""
    },
    {
      "id": "tf100.mapping.203",
      "mapping_id": 203,
      "keyword": 10185,
      "keyword_label": "ConsigneTempSolChauffageGlycol",
      "keyword_type": "CONSIGNE",
      "device_id": 2,
      "device": "NX102 systeme refrigération",
      "protocol_id": 2,
      "protocol": "NX102 OPC UA",
      "addressing_scheme": "OPCUA_NODE",
      "addressing_scheme_label": "OPC UA node id",
      "address_uri": "opcua://ns=4;s=ConsigneTempSolChauffageGlycol",
      "address": {
        "node_id": "ns=4;s=ConsigneTempSolChauffageGlycol"
      },
      "datatype": "FLOAT32",
      "datatype_label": "Float32",
      "writeable": true,
      "enabled": true,
      "historian": false,
      "poll_period_ms": null,
      "unit": "",
      "scale": 1.0,
      "offset": 0.0,
      "scaling": null,
      "notes": ""
    },
    {
      "id": "tf100.mapping.192",
      "mapping_id": 192,
      "keyword": 10274,
      "keyword_label": "Noeud1_N15_00_Commande_MC_140",
      "keyword_type": "SIGNAL",
      "device_id": 2,
      "device": "NX102 systeme refrigération",
      "protocol_id": 2,
      "protocol": "NX102 OPC UA",
      "addressing_scheme": "OPCUA_NODE",
      "addressing_scheme_label": "OPC UA node id",
      "address_uri": "opcua://ns=4;s=Noeud1_N15_00_Commande_MC_140",
      "address": {
        "node_id": "ns=4;s=Noeud1_N15_00_Commande_MC_140"
      },
      "datatype": "BOOL",
      "datatype_label": "Booléen",
      "writeable": false,
      "enabled": true,
      "historian": false,
      "poll_period_ms": null,
      "unit": "",
      "scale": 1.0,
      "offset": 0.0,
      "scaling": null,
      "notes": ""
    },
    {
      "id": "tf100.mapping.193",
      "mapping_id": 193,
      "keyword": 10275,
      "keyword_label": "Noeud1_N15_01_Commande_MC_1A",
      "keyword_type": "SIGNAL",
      "device_id": 2,
      "device": "NX102 systeme refrigération",
      "protocol_id": 2,
      "protocol": "NX102 OPC UA",
      "addressing_scheme": "OPCUA_NODE",
      "addressing_scheme_label": "OPC UA node id",
      "address_uri": "opcua://ns=4;s=Noeud1_N15_01_Commande_MC_1A",
      "address": {
        "node_id": "ns=4;s=Noeud1_N15_01_Commande_MC_1A"
      },
      "datatype": "BOOL",
      "datatype_label": "Booléen",
      "writeable": false,
      "enabled": true,
      "historian": false,
      "poll_period_ms": null,
      "unit": "",
      "scale": 1.0,
      "offset": 0.0,
      "scaling": null,
      "notes": ""
    },
    {
      "id": "tf100.mapping.194",
      "mapping_id": 194,
      "keyword": 10276,
      "keyword_label": "Noeud1_N15_02_Commande_MC_1B",
      "keyword_type": "SIGNAL",
      "device_id": 2,
      "device": "NX102 systeme refrigération",
      "protocol_id": 2,
      "protocol": "NX102 OPC UA",
      "addressing_scheme": "OPCUA_NODE",
      "addressing_scheme_label": "OPC UA node id",
      "address_uri": "opcua://ns=4;s=Noeud1_N15_02_Commande_MC_1B",
      "address": {
        "node_id": "ns=4;s=Noeud1_N15_02_Commande_MC_1B"
      },
      "datatype": "BOOL",
      "datatype_label": "Booléen",
      "writeable": false,
      "enabled": true,
      "historian": false,
      "poll_period_ms": null,
      "unit": "",
      "scale": 1.0,
      "offset": 0.0,
      "scaling": null,
      "notes": ""
    },
    {
      "id": "tf100.mapping.195",
      "mapping_id": 195,
      "keyword": 10277,
      "keyword_label": "Noeud1_N15_03_Commande_MC_120A",
      "keyword_type": "SIGNAL",
      "device_id": 2,
      "device": "NX102 systeme refrigération",
      "protocol_id": 2,
      "protocol": "NX102 OPC UA",
      "addressing_scheme": "OPCUA_NODE",
      "addressing_scheme_label": "OPC UA node id",
      "address_uri": "opcua://ns=4;s=Noeud1_N15_03_Commande_MC_120A",
      "address": {
        "node_id": "ns=4;s=Noeud1_N15_03_Commande_MC_120A"
      },
      "datatype": "BOOL",
      "datatype_label": "Booléen",
      "writeable": false,
      "enabled": true,
      "historian": false,
      "poll_period_ms": null,
      "unit": "",
      "scale": 1.0,
      "offset": 0.0,
      "scaling": null,
      "notes": ""
    },
    {
      "id": "tf100.mapping.196",
      "mapping_id": 196,
      "keyword": 10278,
      "keyword_label": "Noeud1_N15_04_Commande_MC_120C",
      "keyword_type": "SIGNAL",
      "device_id": 2,
      "device": "NX102 systeme refrigération",
      "protocol_id": 2,
      "protocol": "NX102 OPC UA",
      "addressing_scheme": "OPCUA_NODE",
      "addressing_scheme_label": "OPC UA node id",
      "address_uri": "opcua://ns=4;s=Noeud1_N15_04_Commande_MC_120C",
      "address": {
        "node_id": "ns=4;s=Noeud1_N15_04_Commande_MC_120C"
      },
      "datatype": "BOOL",
      "datatype_label": "Booléen",
      "writeable": false,
      "enabled": true,
      "historian": false,
      "poll_period_ms": null,
      "unit": "",
      "scale": 1.0,
      "offset": 0.0,
      "scaling": null,
      "notes": ""
    },
    {
      "id": "tf100.mapping.197",
      "mapping_id": 197,
      "keyword": 10279,
      "keyword_label": "Noeud1_N15_05_Commande_MC_120B",
      "keyword_type": "SIGNAL",
      "device_id": 2,
      "device": "NX102 systeme refrigération",
      "protocol_id": 2,
      "protocol": "NX102 OPC UA",
      "addressing_scheme": "OPCUA_NODE",
      "addressing_scheme_label": "OPC UA node id",
      "address_uri": "opcua://ns=4;s=Noeud1_N15_05_Commande_MC_120B",
      "address": {
        "node_id": "ns=4;s=Noeud1_N15_05_Commande_MC_120B"
      },
      "datatype": "BOOL",
      "datatype_label": "Booléen",
      "writeable": false,
      "enabled": true,
      "historian": false,
      "poll_period_ms": null,
      "unit": "",
      "scale": 1.0,
      "offset": 0.0,
      "scaling": null,
      "notes": ""
    },
    {
      "id": "tf100.mapping.198",
      "mapping_id": 198,
      "keyword": 10280,
      "keyword_label": "Noeud1_N15_06_Commande_MC_110",
      "keyword_type": "SIGNAL",
      "device_id": 2,
      "device": "NX102 systeme refrigération",
      "protocol_id": 2,
      "protocol": "NX102 OPC UA",
      "addressing_scheme": "OPCUA_NODE",
      "addressing_scheme_label": "OPC UA node id",
      "address_uri": "opcua://ns=4;s=Noeud1_N15_06_Commande_MC_110",
      "address": {
        "node_id": "ns=4;s=Noeud1_N15_06_Commande_MC_110"
      },
      "datatype": "BOOL",
      "datatype_label": "Booléen",
      "writeable": false,
      "enabled": true,
      "historian": false,
      "poll_period_ms": null,
      "unit": "",
      "scale": 1.0,
      "offset": 0.0,
      "scaling": null,
      "notes": ""
    },
    {
      "id": "tf100.mapping.199",
      "mapping_id": 199,
      "keyword": 10281,
      "keyword_label": "Noeud1_N15_08_Commande_MC_51B",
      "keyword_type": "SIGNAL",
      "device_id": 2,
      "device": "NX102 systeme refrigération",
      "protocol_id": 2,
      "protocol": "NX102 OPC UA",
      "addressing_scheme": "OPCUA_NODE",
      "addressing_scheme_label": "OPC UA node id",
      "address_uri": "opcua://ns=4;s=Noeud1_N15_08_Commande_MC_51B",
      "address": {
        "node_id": "ns=4;s=Noeud1_N15_08_Commande_MC_51B"
      },
      "datatype": "BOOL",
      "datatype_label": "Booléen",
      "writeable": false,
      "enabled": true,
      "historian": false,
      "poll_period_ms": null,
      "unit": "",
      "scale": 1.0,
      "offset": 0.0,
      "scaling": null,
      "notes": ""
    },
    {
      "id": "tf100.mapping.200",
      "mapping_id": 200,
      "keyword": 10282,
      "keyword_label": "Noeud1_N15_09_Commande_MC_58A",
      "keyword_type": "SIGNAL",
      "device_id": 2,
      "device": "NX102 systeme refrigération",
      "protocol_id": 2,
      "protocol": "NX102 OPC UA",
      "addressing_scheme": "OPCUA_NODE",
      "addressing_scheme_label": "OPC UA node id",
      "address_uri": "opcua://ns=4;s=Noeud1_N15_09_Commande_MC_58A",
      "address": {
        "node_id": "ns=4;s=Noeud1_N15_09_Commande_MC_58A"
      },
      "datatype": "BOOL",
      "datatype_label": "Booléen",
      "writeable": false,
      "enabled": true,
      "historian": false,
      "poll_period_ms": null,
      "unit": "",
      "scale": 1.0,
      "offset": 0.0,
      "scaling": null,
      "notes": ""
    },
    {
      "id": "tf100.mapping.201",
      "mapping_id": 201,
      "keyword": 10283,
      "keyword_label": "Noeud1_N15_10_Commande_MC_58B",
      "keyword_type": "SIGNAL",
      "device_id": 2,
      "device": "NX102 systeme refrigération",
      "protocol_id": 2,
      "protocol": "NX102 OPC UA",
      "addressing_scheme": "OPCUA_NODE",
      "addressing_scheme_label": "OPC UA node id",
      "address_uri": "opcua://ns=4;s=Noeud1_N15_10_Commande_MC_58B",
      "address": {
        "node_id": "ns=4;s=Noeud1_N15_10_Commande_MC_58B"
      },
      "datatype": "BOOL",
      "datatype_label": "Booléen",
      "writeable": false,
      "enabled": true,
      "historian": false,
      "poll_period_ms": null,
      "unit": "",
      "scale": 1.0,
      "offset": 0.0,
      "scaling": null,
      "notes": ""
    },
    {
      "id": "tf100.mapping.202",
      "mapping_id": 202,
      "keyword": 10284,
      "keyword_label": "Noeud1_N15_11_Commande_MC_135",
      "keyword_type": "SIGNAL",
      "device_id": 2,
      "device": "NX102 systeme refrigération",
      "protocol_id": 2,
      "protocol": "NX102 OPC UA",
      "addressing_scheme": "OPCUA_NODE",
      "addressing_scheme_label": "OPC UA node id",
      "address_uri": "opcua://ns=4;s=Noeud1_N15_11_Commande_MC_135",
      "address": {
        "node_id": "ns=4;s=Noeud1_N15_11_Commande_MC_135"
      },
      "datatype": "BOOL",
      "datatype_label": "Booléen",
      "writeable": false,
      "enabled": true,
      "historian": false,
      "poll_period_ms": null,
      "unit": "",
      "scale": 1.0,
      "offset": 0.0,
      "scaling": null,
      "notes": ""
    },
    {
      "id": "tf100.mapping.168",
      "mapping_id": 168,
      "keyword": 10100,
      "keyword_label": "TE-800",
      "keyword_type": "LECTURE",
      "device_id": 2,
      "device": "NX102 systeme refrigération",
      "protocol_id": 2,
      "protocol": "NX102 OPC UA",
      "addressing_scheme": "OPCUA_NODE",
      "addressing_scheme_label": "OPC UA node id",
      "address_uri": "opcua://ns=4;s=TE_800",
      "address": {
        "node_id": "ns=4;s=TE_800"
      },
      "datatype": "FLOAT32",
      "datatype_label": "Float32",
      "writeable": false,
      "enabled": true,
      "historian": false,
      "poll_period_ms": null,
      "unit": "",
      "scale": 1.0,
      "offset": 0.0,
      "scaling": null,
      "notes": ""
    },
    {
      "id": "tf100.mapping.169",
      "mapping_id": 169,
      "keyword": 10101,
      "keyword_label": "TE-900",
      "keyword_type": "LECTURE",
      "device_id": 2,
      "device": "NX102 systeme refrigération",
      "protocol_id": 2,
      "protocol": "NX102 OPC UA",
      "addressing_scheme": "OPCUA_NODE",
      "addressing_scheme_label": "OPC UA node id",
      "address_uri": "opcua://ns=4;s=TE_900",
      "address": {
        "node_id": "ns=4;s=TE_900"
      },
      "datatype": "FLOAT32",
      "datatype_label": "Float32",
      "writeable": false,
      "enabled": true,
      "historian": false,
      "poll_period_ms": null,
      "unit": "",
      "scale": 1.0,
      "offset": 0.0,
      "scaling": null,
      "notes": ""
    },
    {
      "id": "tf100.mapping.170",
      "mapping_id": 170,
      "keyword": 10104,
      "keyword_label": "TE-Q1",
      "keyword_type": "LECTURE",
      "device_id": 2,
      "device": "NX102 systeme refrigération",
      "protocol_id": 2,
      "protocol": "NX102 OPC UA",
      "addressing_scheme": "OPCUA_NODE",
      "addressing_scheme_label": "OPC UA node id",
      "address_uri": "opcua://ns=4;s=TE_Q1",
      "address": {
        "node_id": "ns=4;s=TE_Q1"
      },
      "datatype": "FLOAT32",
      "datatype_label": "Float32",
      "writeable": false,
      "enabled": true,
      "historian": false,
      "poll_period_ms": null,
      "unit": "",
      "scale": 1.0,
      "offset": 0.0,
      "scaling": null,
      "notes": ""
    },
    {
      "id": "tf100.mapping.171",
      "mapping_id": 171,
      "keyword": 10105,
      "keyword_label": "TE-Q2",
      "keyword_type": "LECTURE",
      "device_id": 2,
      "device": "NX102 systeme refrigération",
      "protocol_id": 2,
      "protocol": "NX102 OPC UA",
      "addressing_scheme": "OPCUA_NODE",
      "addressing_scheme_label": "OPC UA node id",
      "address_uri": "opcua://ns=4;s=TE_Q2",
      "address": {
        "node_id": "ns=4;s=TE_Q2"
      },
      "datatype": "FLOAT32",
      "datatype_label": "Float32",
      "writeable": false,
      "enabled": true,
      "historian": false,
      "poll_period_ms": null,
      "unit": "",
      "scale": 1.0,
      "offset": 0.0,
      "scaling": null,
      "notes": ""
    },
    {
      "id": "tf100.mapping.172",
      "mapping_id": 172,
      "keyword": 10106,
      "keyword_label": "TE-Q3",
      "keyword_type": "LECTURE",
      "device_id": 2,
      "device": "NX102 systeme refrigération",
      "protocol_id": 2,
      "protocol": "NX102 OPC UA",
      "addressing_scheme": "OPCUA_NODE",
      "addressing_scheme_label": "OPC UA node id",
      "address_uri": "opcua://ns=4;s=TE_Q3",
      "address": {
        "node_id": "ns=4;s=TE_Q3"
      },
      "datatype": "FLOAT32",
      "datatype_label": "Float32",
      "writeable": false,
      "enabled": true,
      "historian": false,
      "poll_period_ms": null,
      "unit": "",
      "scale": 1.0,
      "offset": 0.0,
      "scaling": null,
      "notes": ""
    },
    {
      "id": "tf100.mapping.173",
      "mapping_id": 173,
      "keyword": 10107,
      "keyword_label": "TE-Q4",
      "keyword_type": "LECTURE",
      "device_id": 2,
      "device": "NX102 systeme refrigération",
      "protocol_id": 2,
      "protocol": "NX102 OPC UA",
      "addressing_scheme": "OPCUA_NODE",
      "addressing_scheme_label": "OPC UA node id",
      "address_uri": "opcua://ns=4;s=TE_Q4",
      "address": {
        "node_id": "ns=4;s=TE_Q4"
      },
      "datatype": "FLOAT32",
      "datatype_label": "Float32",
      "writeable": false,
      "enabled": true,
      "historian": false,
      "poll_period_ms": null,
      "unit": "",
      "scale": 1.0,
      "offset": 0.0,
      "scaling": null,
      "notes": ""
    },
    {
      "id": "tf100.mapping.174",
      "mapping_id": 174,
      "keyword": 10108,
      "keyword_label": "TE-Q5",
      "keyword_type": "LECTURE",
      "device_id": 2,
      "device": "NX102 systeme refrigération",
      "protocol_id": 2,
      "protocol": "NX102 OPC UA",
      "addressing_scheme": "OPCUA_NODE",
      "addressing_scheme_label": "OPC UA node id",
      "address_uri": "opcua://ns=4;s=TE_Q5",
      "address": {
        "node_id": "ns=4;s=TE_Q5"
      },
      "datatype": "FLOAT32",
      "datatype_label": "Float32",
      "writeable": false,
      "enabled": true,
      "historian": false,
      "poll_period_ms": null,
      "unit": "",
      "scale": 1.0,
      "offset": 0.0,
      "scaling": null,
      "notes": ""
    },
    {
      "id": "tf100.mapping.175",
      "mapping_id": 175,
      "keyword": 10109,
      "keyword_label": "TE-Q6",
      "keyword_type": "LECTURE",
      "device_id": 2,
      "device": "NX102 systeme refrigération",
      "protocol_id": 2,
      "protocol": "NX102 OPC UA",
      "addressing_scheme": "OPCUA_NODE",
      "addressing_scheme_label": "OPC UA node id",
      "address_uri": "opcua://ns=4;s=TE_Q6",
      "address": {
        "node_id": "ns=4;s=TE_Q6"
      },
      "datatype": "FLOAT32",
      "datatype_label": "Float32",
      "writeable": false,
      "enabled": true,
      "historian": false,
      "poll_period_ms": null,
      "unit": "",
      "scale": 1.0,
      "offset": 0.0,
      "scaling": null,
      "notes": ""
    },
    {
      "id": "tf100.mapping.176",
      "mapping_id": 176,
      "keyword": 10110,
      "keyword_label": "TE-Q7",
      "keyword_type": "LECTURE",
      "device_id": 2,
      "device": "NX102 systeme refrigération",
      "protocol_id": 2,
      "protocol": "NX102 OPC UA",
      "addressing_scheme": "OPCUA_NODE",
      "addressing_scheme_label": "OPC UA node id",
      "address_uri": "opcua://ns=4;s=TE_Q7",
      "address": {
        "node_id": "ns=4;s=TE_Q7"
      },
      "datatype": "FLOAT32",
      "datatype_label": "Float32",
      "writeable": false,
      "enabled": true,
      "historian": false,
      "poll_period_ms": null,
      "unit": "",
      "scale": 1.0,
      "offset": 0.0,
      "scaling": null,
      "notes": ""
    },
    {
      "id": "tf100.mapping.177",
      "mapping_id": 177,
      "keyword": 10111,
      "keyword_label": "TE-Q8",
      "keyword_type": "LECTURE",
      "device_id": 2,
      "device": "NX102 systeme refrigération",
      "protocol_id": 2,
      "protocol": "NX102 OPC UA",
      "addressing_scheme": "OPCUA_NODE",
      "addressing_scheme_label": "OPC UA node id",
      "address_uri": "opcua://ns=4;s=TE_Q8",
      "address": {
        "node_id": "ns=4;s=TE_Q8"
      },
      "datatype": "FLOAT32",
      "datatype_label": "Float32",
      "writeable": false,
      "enabled": true,
      "historian": false,
      "poll_period_ms": null,
      "unit": "",
      "scale": 1.0,
      "offset": 0.0,
      "scaling": null,
      "notes": ""
    },
    {
      "id": "tf100.mapping.178",
      "mapping_id": 178,
      "keyword": 10112,
      "keyword_label": "TE-R1",
      "keyword_type": "LECTURE",
      "device_id": 2,
      "device": "NX102 systeme refrigération",
      "protocol_id": 2,
      "protocol": "NX102 OPC UA",
      "addressing_scheme": "OPCUA_NODE",
      "addressing_scheme_label": "OPC UA node id",
      "address_uri": "opcua://ns=4;s=TE_R1",
      "address": {
        "node_id": "ns=4;s=TE_R1"
      },
      "datatype": "FLOAT32",
      "datatype_label": "Float32",
      "writeable": false,
      "enabled": true,
      "historian": false,
      "poll_period_ms": null,
      "unit": "",
      "scale": 1.0,
      "offset": 0.0,
      "scaling": null,
      "notes": ""
    },
    {
      "id": "tf100.mapping.179",
      "mapping_id": 179,
      "keyword": 10113,
      "keyword_label": "TE-R2",
      "keyword_type": "LECTURE",
      "device_id": 2,
      "device": "NX102 systeme refrigération",
      "protocol_id": 2,
      "protocol": "NX102 OPC UA",
      "addressing_scheme": "OPCUA_NODE",
      "addressing_scheme_label": "OPC UA node id",
      "address_uri": "opcua://ns=4;s=TE_R2",
      "address": {
        "node_id": "ns=4;s=TE_R2"
      },
      "datatype": "FLOAT32",
      "datatype_label": "Float32",
      "writeable": false,
      "enabled": true,
      "historian": false,
      "poll_period_ms": null,
      "unit": "",
      "scale": 1.0,
      "offset": 0.0,
      "scaling": null,
      "notes": ""
    },
    {
      "id": "tf100.mapping.180",
      "mapping_id": 180,
      "keyword": 10114,
      "keyword_label": "TE-R3",
      "keyword_type": "LECTURE",
      "device_id": 2,
      "device": "NX102 systeme refrigération",
      "protocol_id": 2,
      "protocol": "NX102 OPC UA",
      "addressing_scheme": "OPCUA_NODE",
      "addressing_scheme_label": "OPC UA node id",
      "address_uri": "opcua://ns=4;s=TE_R3",
      "address": {
        "node_id": "ns=4;s=TE_R3"
      },
      "datatype": "FLOAT32",
      "datatype_label": "Float32",
      "writeable": false,
      "enabled": true,
      "historian": false,
      "poll_period_ms": null,
      "unit": "",
      "scale": 1.0,
      "offset": 0.0,
      "scaling": null,
      "notes": ""
    },
    {
      "id": "tf100.mapping.181",
      "mapping_id": 181,
      "keyword": 10115,
      "keyword_label": "TE-R4",
      "keyword_type": "LECTURE",
      "device_id": 2,
      "device": "NX102 systeme refrigération",
      "protocol_id": 2,
      "protocol": "NX102 OPC UA",
      "addressing_scheme": "OPCUA_NODE",
      "addressing_scheme_label": "OPC UA node id",
      "address_uri": "opcua://ns=4;s=TE_R4",
      "address": {
        "node_id": "ns=4;s=TE_R4"
      },
      "datatype": "FLOAT32",
      "datatype_label": "Float32",
      "writeable": false,
      "enabled": true,
      "historian": false,
      "poll_period_ms": null,
      "unit": "",
      "scale": 1.0,
      "offset": 0.0,
      "scaling": null,
      "notes": ""
    },
    {
      "id": "tf100.mapping.182",
      "mapping_id": 182,
      "keyword": 10116,
      "keyword_label": "TE-C1",
      "keyword_type": "LECTURE",
      "device_id": 2,
      "device": "NX102 systeme refrigération",
      "protocol_id": 2,
      "protocol": "NX102 OPC UA",
      "addressing_scheme": "OPCUA_NODE",
      "addressing_scheme_label": "OPC UA node id",
      "address_uri": "opcua://ns=4;s=TE_C1",
      "address": {
        "node_id": "ns=4;s=TE_C1"
      },
      "datatype": "FLOAT32",
      "datatype_label": "Float32",
      "writeable": false,
      "enabled": true,
      "historian": false,
      "poll_period_ms": null,
      "unit": "",
      "scale": 1.0,
      "offset": 0.0,
      "scaling": null,
      "notes": ""
    },
    {
      "id": "tf100.mapping.183",
      "mapping_id": 183,
      "keyword": 10117,
      "keyword_label": "TE-C2",
      "keyword_type": "LECTURE",
      "device_id": 2,
      "device": "NX102 systeme refrigération",
      "protocol_id": 2,
      "protocol": "NX102 OPC UA",
      "addressing_scheme": "OPCUA_NODE",
      "addressing_scheme_label": "OPC UA node id",
      "address_uri": "opcua://ns=4;s=TE_C2",
      "address": {
        "node_id": "ns=4;s=TE_C2"
      },
      "datatype": "FLOAT32",
      "datatype_label": "Float32",
      "writeable": false,
      "enabled": true,
      "historian": false,
      "poll_period_ms": null,
      "unit": "",
      "scale": 1.0,
      "offset": 0.0,
      "scaling": null,
      "notes": ""
    },
    {
      "id": "tf100.mapping.184",
      "mapping_id": 184,
      "keyword": 10118,
      "keyword_label": "TE-C3",
      "keyword_type": "LECTURE",
      "device_id": 2,
      "device": "NX102 systeme refrigération",
      "protocol_id": 2,
      "protocol": "NX102 OPC UA",
      "addressing_scheme": "OPCUA_NODE",
      "addressing_scheme_label": "OPC UA node id",
      "address_uri": "opcua://ns=4;s=TE_C3",
      "address": {
        "node_id": "ns=4;s=TE_C3"
      },
      "datatype": "FLOAT32",
      "datatype_label": "Float32",
      "writeable": false,
      "enabled": true,
      "historian": false,
      "poll_period_ms": null,
      "unit": "",
      "scale": 1.0,
      "offset": 0.0,
      "scaling": null,
      "notes": ""
    },
    {
      "id": "tf100.mapping.185",
      "mapping_id": 185,
      "keyword": 10119,
      "keyword_label": "TE-C4",
      "keyword_type": "LECTURE",
      "device_id": 2,
      "device": "NX102 systeme refrigération",
      "protocol_id": 2,
      "protocol": "NX102 OPC UA",
      "addressing_scheme": "OPCUA_NODE",
      "addressing_scheme_label": "OPC UA node id",
      "address_uri": "opcua://ns=4;s=TE_C4",
      "address": {
        "node_id": "ns=4;s=TE_C4"
      },
      "datatype": "FLOAT32",
      "datatype_label": "Float32",
      "writeable": false,
      "enabled": true,
      "historian": false,
      "poll_period_ms": null,
      "unit": "",
      "scale": 1.0,
      "offset": 0.0,
      "scaling": null,
      "notes": ""
    },
    {
      "id": "tf100.mapping.186",
      "mapping_id": 186,
      "keyword": 10120,
      "keyword_label": "TE-C5",
      "keyword_type": "LECTURE",
      "device_id": 2,
      "device": "NX102 systeme refrigération",
      "protocol_id": 2,
      "protocol": "NX102 OPC UA",
      "addressing_scheme": "OPCUA_NODE",
      "addressing_scheme_label": "OPC UA node id",
      "address_uri": "opcua://ns=4;s=TE_C5",
      "address": {
        "node_id": "ns=4;s=TE_C5"
      },
      "datatype": "FLOAT32",
      "datatype_label": "Float32",
      "writeable": false,
      "enabled": true,
      "historian": false,
      "poll_period_ms": null,
      "unit": "",
      "scale": 1.0,
      "offset": 0.0,
      "scaling": null,
      "notes": ""
    },
    {
      "id": "tf100.mapping.187",
      "mapping_id": 187,
      "keyword": 10121,
      "keyword_label": "TE-C6",
      "keyword_type": "LECTURE",
      "device_id": 2,
      "device": "NX102 systeme refrigération",
      "protocol_id": 2,
      "protocol": "NX102 OPC UA",
      "addressing_scheme": "OPCUA_NODE",
      "addressing_scheme_label": "OPC UA node id",
      "address_uri": "opcua://ns=4;s=TE_C6",
      "address": {
        "node_id": "ns=4;s=TE_C6"
      },
      "datatype": "FLOAT32",
      "datatype_label": "Float32",
      "writeable": false,
      "enabled": true,
      "historian": false,
      "poll_period_ms": null,
      "unit": "",
      "scale": 1.0,
      "offset": 0.0,
      "scaling": null,
      "notes": ""
    },
    {
      "id": "tf100.mapping.188",
      "mapping_id": 188,
      "keyword": 10122,
      "keyword_label": "TE-C7",
      "keyword_type": "LECTURE",
      "device_id": 2,
      "device": "NX102 systeme refrigération",
      "protocol_id": 2,
      "protocol": "NX102 OPC UA",
      "addressing_scheme": "OPCUA_NODE",
      "addressing_scheme_label": "OPC UA node id",
      "address_uri": "opcua://ns=4;s=TE_C7",
      "address": {
        "node_id": "ns=4;s=TE_C7"
      },
      "datatype": "FLOAT32",
      "datatype_label": "Float32",
      "writeable": false,
      "enabled": true,
      "historian": false,
      "poll_period_ms": null,
      "unit": "",
      "scale": 1.0,
      "offset": 0.0,
      "scaling": null,
      "notes": ""
    },
    {
      "id": "tf100.mapping.189",
      "mapping_id": 189,
      "keyword": 10123,
      "keyword_label": "TE-C8",
      "keyword_type": "LECTURE",
      "device_id": 2,
      "device": "NX102 systeme refrigération",
      "protocol_id": 2,
      "protocol": "NX102 OPC UA",
      "addressing_scheme": "OPCUA_NODE",
      "addressing_scheme_label": "OPC UA node id",
      "address_uri": "opcua://ns=4;s=TE_C8",
      "address": {
        "node_id": "ns=4;s=TE_C8"
      },
      "datatype": "FLOAT32",
      "datatype_label": "Float32",
      "writeable": false,
      "enabled": true,
      "historian": false,
      "poll_period_ms": null,
      "unit": "",
      "scale": 1.0,
      "offset": 0.0,
      "scaling": null,
      "notes": ""
    },
    {
      "id": "tf100.mapping.190",
      "mapping_id": 190,
      "keyword": 10124,
      "keyword_label": "TE-C9",
      "keyword_type": "LECTURE",
      "device_id": 2,
      "device": "NX102 systeme refrigération",
      "protocol_id": 2,
      "protocol": "NX102 OPC UA",
      "addressing_scheme": "OPCUA_NODE",
      "addressing_scheme_label": "OPC UA node id",
      "address_uri": "opcua://ns=4;s=TE_C9",
      "address": {
        "node_id": "ns=4;s=TE_C9"
      },
      "datatype": "FLOAT32",
      "datatype_label": "Float32",
      "writeable": false,
      "enabled": true,
      "historian": false,
      "poll_period_ms": null,
      "unit": "",
      "scale": 1.0,
      "offset": 0.0,
      "scaling": null,
      "notes": ""
    },
    {
      "id": "tf100.mapping.191",
      "mapping_id": 191,
      "keyword": 10125,
      "keyword_label": "TE-C10",
      "keyword_type": "LECTURE",
      "device_id": 2,
      "device": "NX102 systeme refrigération",
      "protocol_id": 2,
      "protocol": "NX102 OPC UA",
      "addressing_scheme": "OPCUA_NODE",
      "addressing_scheme_label": "OPC UA node id",
      "address_uri": "opcua://ns=4;s=TE_C10",
      "address": {
        "node_id": "ns=4;s=TE_C10"
      },
      "datatype": "FLOAT32",
      "datatype_label": "Float32",
      "writeable": false,
      "enabled": true,
      "historian": false,
      "poll_period_ms": null,
      "unit": "",
      "scale": 1.0,
      "offset": 0.0,
      "scaling": null,
      "notes": ""
    }
  ]
}
